pipguitool/PIP.py
pipguitool/__init__.py
pipguitool/server.py
pipguitool/static/bootstrap-grid.css
pipguitool/static/bootstrap-grid.css.map
pipguitool/static/bootstrap-grid.min.css
pipguitool/static/bootstrap-grid.min.css.map
pipguitool/static/bootstrap-reboot.css
pipguitool/static/bootstrap-reboot.css.map
pipguitool/static/bootstrap-reboot.min.css
pipguitool/static/bootstrap-reboot.min.css.map
pipguitool/static/bootstrap.bundle.js
pipguitool/static/bootstrap.bundle.js.map
pipguitool/static/bootstrap.bundle.min.js
pipguitool/static/bootstrap.bundle.min.js.map
pipguitool/static/bootstrap.css
pipguitool/static/bootstrap.css.map
pipguitool/static/bootstrap.js
pipguitool/static/bootstrap.js.map
pipguitool/static/bootstrap.min.css
pipguitool/static/bootstrap.min.css.map
pipguitool/static/bootstrap.min.js
pipguitool/static/bootstrap.min.js.map
pipguitool/static/jquery-3.5.1.min.js
pipguitool/templates/index.html
pip_gui_tools-0.0.10.dist-info/LICENSE.txt
pip_gui_tools-0.0.10.dist-info/METADATA
pip_gui_tools-0.0.10.dist-info/WHEEL
pip_gui_tools-0.0.10.dist-info/entry_points.txt
pip_gui_tools-0.0.10.dist-info/top_level.txt
pip_gui_tools-0.0.10.dist-info/RECORD
